aiogram3_di/__init__.py
aiogram3_di/depends.py
aiogram3_di/manager.py
aiogram3_di/middleware.py
aiogram3_di/resolver.py
aiogram3_di/setup.py
aiogram3_di/utils.py
aiogram3_di-2.0.0.dist-info/LICENSE
aiogram3_di-2.0.0.dist-info/METADATA
aiogram3_di-2.0.0.dist-info/WHEEL
aiogram3_di-2.0.0.dist-info/RECORD
