Metadata-Version: 2.1
Name: aiogram3-di
Version: 2.0.0
Summary: Dependency Injection implementation for aiogram 3.
Home-page: https://github.com/Vladyslav49/aiogram3_di
License: MIT
Keywords: Aiogram,Telegram,Bots,DI,Dependency Injection
Author: Vladyslav Timofeev
Author-email: Timofeevvladyslav49@gmail.com
Requires-Python: >=3.10
Classifier: Intended Audience :: Developers
Classifier: License :: OSI Approved :: MIT License
Classifier: Operating System :: OS Independent
Classifier: Programming Language :: Python :: 3
Classifier: Programming Language :: Python :: 3.10
Classifier: Programming Language :: Python :: 3.11
Classifier: Programming Language :: Python :: 3.12
Requires-Dist: aiogram (>=3.0.0)
Project-URL: Repository, https://github.com/Vladyslav49/aiogram3_di
